Alpha_Rabbit/Alpha_Rabbit.py
Alpha_Rabbit/Factor_Calculator.py
Alpha_Rabbit/Factor_Def_and_Get_Method.py
Alpha_Rabbit/__init__.py
Alpha_Rabbit/trade_strategy.py
Alpha_Rabbit-1.4.17.dist-info/LICENSE.txt
Alpha_Rabbit-1.4.17.dist-info/METADATA
Alpha_Rabbit-1.4.17.dist-info/WHEEL
Alpha_Rabbit-1.4.17.dist-info/top_level.txt
Alpha_Rabbit-1.4.17.dist-info/zip-safe
Alpha_Rabbit-1.4.17.dist-info/RECORD
