Metadata-Version: 2.1
Name: Alpha-Rabbit
Version: 1.4.17
Summary: Alpha_Rabbit
Home-page: 
Author: lijiongting
Author-email: 448986334@qq.com
License: MIT
Classifier: Intended Audience :: Developers
Classifier: License :: OSI Approved :: MIT License
Classifier: Operating System :: MacOS
Classifier: Operating System :: Microsoft
Classifier: Operating System :: POSIX
Classifier: Operating System :: Unix
Classifier: Topic :: Software Development :: Libraries :: Python Modules
Classifier: Programming Language :: Python :: 3.7
Classifier: Programming Language :: Python :: 3.8
Requires-Python: >=3.8
License-File: LICENSE.txt
Requires-Dist: statsmodels (>=0.13.2)
Requires-Dist: numpy (>=1.23.2)
Requires-Dist: pandas (>=1.4.4)
